jupyter-config/jupyter_notebook_config/jupyter_mcp_server.json
jupyter-config/jupyter_server_config.d/jupyter_mcp_server.json
jupyter_mcp_server/CLI.py
jupyter_mcp_server/__init__.py
jupyter_mcp_server/__main__.py
jupyter_mcp_server/__version__.py
jupyter_mcp_server/config.py
jupyter_mcp_server/enroll.py
jupyter_mcp_server/log.py
jupyter_mcp_server/models.py
jupyter_mcp_server/notebook_manager.py
jupyter_mcp_server/server.py
jupyter_mcp_server/server_context.py
jupyter_mcp_server/server_modes.py
jupyter_mcp_server/tool_cache.py
jupyter_mcp_server/utils.py
jupyter_mcp_server/jupyter_extension/__init__.py
jupyter_mcp_server/jupyter_extension/context.py
jupyter_mcp_server/jupyter_extension/extension.py
jupyter_mcp_server/jupyter_extension/handlers.py
jupyter_mcp_server/jupyter_extension/backends/__init__.py
jupyter_mcp_server/jupyter_extension/backends/base.py
jupyter_mcp_server/jupyter_extension/backends/local_backend.py
jupyter_mcp_server/jupyter_extension/backends/remote_backend.py
jupyter_mcp_server/jupyter_extension/protocol/__init__.py
jupyter_mcp_server/jupyter_extension/protocol/messages.py
jupyter_mcp_server/tools/__init__.py
jupyter_mcp_server/tools/_base.py
jupyter_mcp_server/tools/delete_cell_tool.py
jupyter_mcp_server/tools/execute_cell_tool.py
jupyter_mcp_server/tools/execute_code_tool.py
jupyter_mcp_server/tools/insert_cell_tool.py
jupyter_mcp_server/tools/jupyter_cite_prompt.py
jupyter_mcp_server/tools/list_files_tool.py
jupyter_mcp_server/tools/list_kernels_tool.py
jupyter_mcp_server/tools/list_notebooks_tool.py
jupyter_mcp_server/tools/overwrite_cell_source_tool.py
jupyter_mcp_server/tools/read_cell_tool.py
jupyter_mcp_server/tools/read_notebook_tool.py
jupyter_mcp_server/tools/restart_notebook_tool.py
jupyter_mcp_server/tools/unuse_notebook_tool.py
jupyter_mcp_server/tools/use_notebook_tool.py
jupyter_mcp_server-0.22.0.data/data/etc/jupyter/jupyter_server_config.d/jupyter_mcp_server.json
jupyter_mcp_server-0.22.0.dist-info/METADATA
jupyter_mcp_server-0.22.0.dist-info/WHEEL
jupyter_mcp_server-0.22.0.dist-info/entry_points.txt
jupyter_mcp_server-0.22.0.dist-info/licenses/LICENSE
jupyter_mcp_server-0.22.0.dist-info/RECORD
