Metadata-Version: 2.4
Name: jupyter_mcp_server
Version: 0.22.0
Project-URL: Home, https://github.com/datalayer/jupyter-mcp-server
Author-email: Datalayer <info@datalayer.io>
License: BSD 3-Clause License
License-File: LICENSE
Keywords: Jupyter
Classifier: Intended Audience :: Developers
Classifier: Intended Audience :: System Administrators
Classifier: License :: OSI Approved :: BSD License
Classifier: Programming Language :: Python
Classifier: Programming Language :: Python :: 3
Requires-Python: >=3.10
Requires-Dist: click
Requires-Dist: fastapi
Requires-Dist: jupyter-kernel-client>=0.7.3
Requires-Dist: jupyter-mcp-tools>=0.1.6
Requires-Dist: jupyter-nbmodel-client>=0.14.4
Requires-Dist: jupyter-server-client
Requires-Dist: jupyter-server-nbmodel>=0.1.1a4
Requires-Dist: jupyter-server<3,>=1.6
Requires-Dist: mcp[cli]>=1.10.1
Requires-Dist: pydantic
Requires-Dist: tornado>=6.1
Requires-Dist: traitlets>=5.0
Requires-Dist: uvicorn
Provides-Extra: lint
Requires-Dist: mdformat-gfm>=0.3.5; extra == 'lint'
Requires-Dist: mdformat>0.7; extra == 'lint'
Requires-Dist: ruff; extra == 'lint'
Provides-Extra: test
Requires-Dist: datalayer-pycrdt==0.12.17; extra == 'test'
Requires-Dist: ipykernel; extra == 'test'
Requires-Dist: jupyter-collaboration==4.0.2; extra == 'test'
Requires-Dist: jupyter-server<3,>=1.6; extra == 'test'
Requires-Dist: jupyterlab==4.4.1; extra == 'test'
Requires-Dist: pillow>=10.0.0; extra == 'test'
Requires-Dist: pytest-asyncio; extra == 'test'
Requires-Dist: pytest-timeout>=2.1.0; extra == 'test'
Requires-Dist: pytest>=7.0; extra == 'test'
Provides-Extra: typing
Requires-Dist: mypy>=0.990; extra == 'typing'
